ff/__init__.py
ff/cli.py
ff/create_validate_secret_in_gcp.py
ff/example.py
ffnostrame-0.0.7.dist-info/LICENSE
ffnostrame-0.0.7.dist-info/METADATA
ffnostrame-0.0.7.dist-info/WHEEL
ffnostrame-0.0.7.dist-info/entry_points.txt
ffnostrame-0.0.7.dist-info/top_level.txt
ffnostrame-0.0.7.dist-info/RECORD
