Metadata-Version: 2.1
Name: ffnostrame
Version: 0.0.7
License-File: LICENSE
Requires-Dist: click-shell (==2.1)
Requires-Dist: rich-click (==1.5.1)
Requires-Dist: click (==7.1.2)
